odoo/addons/commission_report_settlement_grouped/README.rst
odoo/addons/commission_report_settlement_grouped/__init__.py
odoo/addons/commission_report_settlement_grouped/__manifest__.py
odoo/addons/commission_report_settlement_grouped/i18n/es.po
odoo/addons/commission_report_settlement_grouped/models/__init__.py
odoo/addons/commission_report_settlement_grouped/models/account_move.py
odoo/addons/commission_report_settlement_grouped/report/commission_report_settlement_grouped.xml
odoo/addons/commission_report_settlement_grouped/static/description/icon.png
odoo_addon_commission_report_settlement_grouped-15.0.1.0.0.4.dist-info/METADATA
odoo_addon_commission_report_settlement_grouped-15.0.1.0.0.4.dist-info/WHEEL
odoo_addon_commission_report_settlement_grouped-15.0.1.0.0.4.dist-info/top_level.txt
odoo_addon_commission_report_settlement_grouped-15.0.1.0.0.4.dist-info/RECORD
