Metadata-Version: 2.1
Name: odoo-addon-commission_report_settlement_grouped
Version: 15.0.1.0.0.4
Requires-Python: >=3.8
Requires-Dist: odoo-addon-account_commission>=15.0dev,<15.1dev
Requires-Dist: odoo>=15.0a,<15.1dev
Summary: Adds new settlement report that groups lines by invoice.
Home-page: https://github.com/sygel-technology/sy-commission
License: AGPL-3
Author: Sygel
Classifier: Programming Language :: Python
Classifier: Framework :: Odoo
Classifier: Framework :: Odoo :: 15.0
Classifier: License :: OSI Approved :: GNU Affero General Public License v3
